sthg_common_base_plus/__init__.py
sthg_common_base_plus/example/__init__.py
sthg_common_base_plus/example/test_fastapi.py
sthg_common_base_plus/example/test_service.py
sthg_common_base_plus/example/test_utils.py
sthg_common_base_plus/foundry_common/__init__.py
sthg_common_base_plus/foundry_common/foundry_type.py
sthg_common_base_plus/foundry_common/generator.py
sthg_common_base_plus/response/__init__.py
sthg_common_base_plus/response/exception.py
sthg_common_base_plus/response/httpCodeEnum.py
sthg_common_base_plus/response/json_serializer.py
sthg_common_base_plus/response/response.py
sthg_common_base_plus/test/api_test.py
sthg_common_base_plus/test/test_http_code_enum.py
sthg_common_base_plus/test/util.py
sthg_common_base_plus/utils/__init__.py
sthg_common_base_plus/utils/access_info.py
sthg_common_base_plus/utils/code_utils.py
sthg_common_base_plus/utils/constants.py
sthg_common_base_plus/utils/log_util.py
sthg_common_base_plus/utils/log_wrapper.py
sthg_common_base_plus/utils/request_util.py
sthg_common_base_plus/utils/sthg_common_constants.py
sthg_common_base_plus/utils/utils.py
sthg_common_base_plus/utils/vliad_common.py
sthg_common_base_plus-0.4.8.8.dist-info/METADATA
sthg_common_base_plus-0.4.8.8.dist-info/WHEEL
sthg_common_base_plus-0.4.8.8.dist-info/top_level.txt
sthg_common_base_plus-0.4.8.8.dist-info/RECORD
